{
  "name": "Montcuq 1 & 2",
  "slug": "montcuq_1_2",
  "technology": "Fixed",
  "capacityMw": 21.33504,
  "commissioningYear": 2029,
  "scenario": {
    "name": "Base Case (BP réel — Inp_Assumption 2026-Q2)",
    "capex": 0,
    "opex": 0,
    "debtRate": 0,
    "surfaceHa": 26.15,
    "yieldP90Mwh": null,
    "yieldMwh": 1327,
    "tariff": 69,
    "projectLifeYears": 35,
    "degradationRate": 0.4,
    "discountRate": 7.5,
    "debtInterestRate": 4.35,
    "debtMaturityYears": 24,
    "tariffInflationRate": 0.4,
    "opexInflationRate": 2,
    "contractDuration": 20,
    "constructionYears": 1,
    "assuranceRate": 2.5,
    "inflationAssurance": 2,
    "balancingCost": 2,
    "omFixedEuroKwc": 5.111458328711669,
    "mraEuroKwc": 1.0931259323380917,
    "backOfficeKeuro": 22.5,
    "diversOpexKeuro": 14.98224,
    "loyerMode": "euroParHa",
    "loyerValeur": 1800,
    "loyerInflation": 0.4,
    "inflationOM": 2,
    "inflationMRA": 2,
    "inflationBackOffice": 2,
    "inflationDivers": 2,
    "methodeTaxes": "appreciation_directe",
    "tauxTFCommune": 0.3568309,
    "tauxTFEPCI": 0.08710000000000001,
    "tauxTSE": 0.00249,
    "tauxGEMAPI": 0.00303,
    "tauxTEOM": 0.146,
    "tauxCFECommune": 0,
    "tauxCFEEPCI": 0.318715,
    "tauxCCI": 0.0112,
    "inflationTaxes": 2,
    "iferRate1": 3.61284,
    "iferRate2": 8.6802,
    "iferRpn": 1.35,
    "inflationAurora": 2,
    "debtTenorYears": 24,
    "gearingMaxPct": 95,
    "tauxIS": 25,
    "amortDuree": 20,
    "ccaRemunRate": 6,
    "dsraMonths": 6,
    "devFeesKEuroPerMW": 110,
    "contingencyRate": 2,
    "prixModuleUSDWc": 0.165,
    "tauxEURUSD": 1.16,
    "boSCtWc": 35.620000000000005,
    "raccordementOuvrageKEuro": 5420,
    "apportAffaireMode": "fixe",
    "apportAffaireValeur": 426.7008,
    "legalFeesKEuro": 10,
    "technicalDDKEuro": 5,
    "arrangerFeesRate": 0.8,
    "participantFeesRate": 0.4,
    "bankFeesPLTKEuroPerMW": 1.5,
    "interimFinancingRate": 2.5,
    "commitmentFeesRate": 0.1,
    "unavailability": 0.01,
    "indemnitesImmoKeuro": 820.45,
    "aleasOpexRate": 0.5,
    "tauxTSECfe": 0.01071,
    "tauxGEMAPICfe": 0.0053,
    "coefDegressif": 2.25,
    "taxeFinaleSizingKeuro": 0,
    "agentFeeAnnuelKeuro": 1,
    "dsrfFeeRate": 1.4000000000000001,
    "capacityCertificateMw": 0.5,
    "goStartYear": 21,
    "goPriceBase": 1,
    "curveIndexAn1": 1.10245,
    "fonciereBienEuroWc": 0.017,
    "batimentsFonciersKeuro": 0,
    "modRetraitementKeuro": 2346.8543999999997,
    "valeurTerrainKeuro": 130.75,
    "dscrSchedule": "[{\"yearFrom\":1,\"yearTo\":20,\"dscrValue\":1.15},{\"yearFrom\":21,\"yearTo\":24,\"dscrValue\":1.4}]",
    "isReference": true
  },
  "engineOnly": {
    "capacityMw": 21.33504,
    "commissioningYear": 2029,
    "investorCurveW": 1,
    "debtSizingCentralW": 0.7,
    "debtSizingLowW": 0.3,
    "unavailability": 0.01,
    "indemnitesImmoKeuro": 820.45,
    "aleasOpexRate": 0.5,
    "tauxTSECfe": 0.01071,
    "tauxGEMAPICfe": 0.0053,
    "coefDegressif": 2.25,
    "taxeFinaleSizingKeuro": 0,
    "agentFeeAnnuelKeuro": 1,
    "dsrfFeeRate": 1.4000000000000001,
    "capacityCertificateMw": 0.5,
    "goStartYear": 21,
    "goPriceBase": 1,
    "curveIndexAn1": 1.10245,
    "fonciereBienEuroWc": 0.017,
    "batimentsFonciersKeuro": 0,
    "modRetraitementKeuro": 2346.8543999999997,
    "valeurTerrainKeuro": 130.75,
    "opexEngagementsKeuroByYear": [
      91.49169960554488,
      93.32153359765579,
      33.374185018454895,
      34.11404077043094,
      34.722502093200475,
      19.14932320163592,
      19.532309665668635,
      20.001293695126552,
      20.32141497616165,
      28.45550523477517,
      16.010749621490188,
      16.415760007107654,
      16.65758390619839,
      16.99073558432236,
      24.690479508256132,
      17.768946562535156,
      18.03070452796756,
      18.391318618526917,
      18.759144990897454,
      37.8528521176518,
      19.517014448529714,
      19.907354737500306,
      20.305501832250318,
      20.81915293052228,
      29.58972395654295,
      21.548360988398695,
      21.979328208166667,
      22.53532067595556,
      22.8672930677766,
      34.807538094243334,
      23.791131707714776,
      24.392955835567243,
      24.752293428706455,
      33.33943522589616,
      36.069708392211055
    ],
    "margeFactFigeeKeuro": null
  },
  "dscrSchedule": [
    {
      "yearFrom": 1,
      "yearTo": 20,
      "dscrValue": 1.15
    },
    {
      "yearFrom": 21,
      "yearTo": 24,
      "dscrValue": 1.4
    }
  ],
  "targets": {
    "capexTotalKeuro": 20700.789224425054,
    "detteKeuro": 15948.495914792717,
    "equityCcaKeuro": 4752.293309632339,
    "gearingPct": 77.0429365851179,
    "maxDebtDscrKeuro": 15948.495914792717,
    "vanBruteKeuro": 1630.7828412838876,
    "trIBrutPct": 10.78294575214386,
    "vanNetteKeuro": -129.3579587161118,
    "investorIrrPct": 7.316292822360995,
    "trIProjetBrutPct": 6.634304821491242,
    "trIProjetNetPct": 5.565491616725921,
    "equityRequiredKeuro": 4752.293309632339
  },
  "flags": [
    "Démantèlement 213350 € an25-30 non modélisé (flux surestimés)",
    "Engagements = BP single-project C_P50 r199 (série appliquée, indexée 2%/an)"
  ]
}